Design.v
`timescale 1ns / 1ps
//////////////////////////////////////////////////////////////////////////////////
// Company: 
// Engineer: 
// 
// Create Date: 23.04.2026 19:56:27
// Design Name: 
// Module Name: aCounter
// Project Name: 
// Target Devices: 
// Tool Versions: 
// Description: 
// 
// Dependencies: 
// 
// Revision:
// Revision 0.01 - File Created
// Additional Comments:
// 
//////////////////////////////////////////////////////////////////////////////////


module aCounter(
   input mode_i,  //0 (UP), 1 (DOWN)
   input clk_i, 
   input rst_i, 
   output [3:0]dout_o
);

//instantiation
wire Qa;
wire Qb;
wire Qc;
wire Qd;
wire QaBar;
wire QbBar;
wire QcBar;
wire QdBar;
wire clkb;
wire clkc;
wire clkd;

//internal connections
assign clkb = mode_i? QaBar : Qa;
assign clkc = mode_i? QbBar : Qb;
assign clkd = mode_i? QcBar : Qc;

assign dout_o = {Qd, Qc, Qb, Qa};

//Structural connections
JKff FF1(.J_i(1'b1), 
   .K_i(1'b1), 
   .clk_i(clk_i), 
   .rst_i(rst_i), 
   .Q_o(Qa), 
   .Qbar_o(QaBar)
);
JKff FF2(.J_i(1'b1), 
   .K_i(1'b1), 
   .clk_i(clkb), 
   .rst_i(rst_i), 
   .Q_o(Qb), 
   .Qbar_o(QbBar)
);
JKff FF3(.J_i(1'b1), 
   .K_i(1'b1), 
   .clk_i(clkc), 
   .rst_i(rst_i), 
   .Q_o(Qc), 
   .Qbar_o(QcBar)
);
JKff FF4(.J_i(1'b1), 
   .K_i(1'b1), 
   .clk_i(clkd), 
   .rst_i(rst_i), 
   .Q_o(Qd), 
   .Qbar_o(QdBar)
);

endmodule

module JKff(
   input J_i, 
   input K_i, 
   input clk_i, 
   input rst_i, 
   output reg Q_o, 
   output Qbar_o
);

assign Qbar_o = ~Q_o;

always@(posedge clk_i) begin
   if(rst_i)  //common if (reset) statement in both designs
      Q_o <= 1'b0;
      
//Design 1
//   else if(J_i && K_i)
//      Q_o <= ~Q_o;
//   else if(J_i == 1'b1 && K_i == 1'b0)
//      Q_o <= 1'b1;
//   else if(J_i == 1'b0 && K_i == 1'b1)
//      Q_o <= 1'b0; */

//Design 2
   else begin
      case({J_i, K_i})
         2'b00: Q_o <= Q_o;
         2'b01: Q_o <= 1'b0;
         2'b10: Q_o <= 1'b1;
         2'b11: Q_o <= ~Q_o;
         default: Q_o <= Q_o;
      endcase
   end
end

endmodule

Testbench.v
`timescale 1ns / 1ps
//////////////////////////////////////////////////////////////////////////////////
// Company: 
// Engineer: 
// 
// Create Date: 23.04.2026 19:56:59
// Design Name: 
// Module Name: tb_aCounter
// Project Name: 
// Target Devices: 
// Tool Versions: 
// Description: 
// 
// Dependencies: 
// 
// Revision:
// Revision 0.01 - File Created
// Additional Comments:
// 
//////////////////////////////////////////////////////////////////////////////////


module tb_aCounter();
reg mode_ti;
reg clk_ti;
reg rst_ti; 
wire [3:0]dout_to;

//net(s)
integer count;
integer pass;
integer fail;
reg [3:0]exp_dout;

//instantiation
aCounter UUT(.mode_i(mode_ti), 
   .clk_i(clk_ti),
   .rst_i(rst_ti),  
   .dout_o(dout_to));

//feeding 
initial begin
mode_ti = 1'b1;
#180 @(posedge clk_ti) mode_ti = 1'b0;
#180 @(posedge clk_ti) mode_ti = 1'b1;
#100 @(posedge clk_ti) mode_ti = 1'b0;
#50 @(posedge clk_ti) mode_ti = 1'b1;
#25 @(posedge clk_ti) mode_ti = 1'b0;

#5 $display("-----------");
$display("Checks: %d, | Pass: %d, Fail: %d", count, pass, fail);
$display("-----------");
#5 $finish;
end

//initialization
initial begin
exp_dout = 4'b0000;
count = 0;
pass = 0;
fail = 0;
end

//capture
initial begin
//$monitor("Time=%0t | mode=%b | dout=%b", $time, mode_ti, dout_to);
$dumpfile("aCounter.vcd");
$dumpvars(0, tb_aCounter);
end

//clock
initial begin
   clk_ti = 1'b0;
   forever
      #5 clk_ti = ~clk_ti;
end

//Reset
initial begin
   rst_ti = 1'b1;
   #10 rst_ti = 1'b0;
end

//auto check
task check; begin 
   if(mode_ti) //UP
      exp_dout = exp_dout + 1;
   else //DOWN
      exp_dout = exp_dout - 1;

   if((exp_dout !== dout_to)) begin //result matching (mismatch)
      $display("Error | Time: %0t, Clock: %b, Reset: %b | Output: %d | Expected Output: %d", $time, clk_ti, rst_ti, dout_to, exp_dout);
      fail = fail + 1;
   end
   else begin////result matching (match)
      pass = pass + 1;
   end
   count = count + 1; //number of checks performed
end
endtask

//running auto checker
always@(posedge clk_ti)
   if(rst_ti)
      exp_dout = 4'b0000;
   else
      #7 check;

endmodule

aCounter.vcd
$date
   Fri Apr 24 17:45:03 2026
$end

$version
  2025.2
  $dumpfile ("aCounter.vcd") 
$end

$timescale
  1ps
$end

$scope module tb_aCounter $end
$var reg 1 ! mode_ti $end
$var reg 1 " clk_ti $end
$var reg 1 # rst_ti $end
$var wire 4 $ dout_to [3:0] $end
$var integer 32 % count [31:0] $end
$var integer 32 & pass [31:0] $end
$var integer 32 ' fail [31:0] $end
$var reg 4 ( exp_dout [3:0] $end
$scope module UUT $end
$var wire 1 ) mode_i $end
$var wire 1 * clk_i $end
$var wire 1 + rst_i $end
$var wire 4 $ dout_o [3:0] $end
$var wire 1 , Qa $end
$var wire 1 - Qb $end
$var wire 1 . Qc $end
$var wire 1 / Qd $end
$var wire 1 0 QaBar $end
$var wire 1 1 QbBar $end
$var wire 1 2 QcBar $end
$var wire 1 3 QdBar $end
$var wire 1 4 clkb $end
$var wire 1 5 clkc $end
$var wire 1 6 clkd $end
$scope module FF1 $end
$var wire 1 7 J_i $end
$var wire 1 8 K_i $end
$var wire 1 * clk_i $end
$var wire 1 + rst_i $end
$var reg 1 9 Q_o $end
$var wire 1 0 Qbar_o $end
$upscope $end
$scope module FF2 $end
$var wire 1 : J_i $end
$var wire 1 ; K_i $end
$var wire 1 4 clk_i $end
$var wire 1 + rst_i $end
$var reg 1 < Q_o $end
$var wire 1 1 Qbar_o $end
$upscope $end
$scope module FF3 $end
$var wire 1 = J_i $end
$var wire 1 > K_i $end
$var wire 1 5 clk_i $end
$var wire 1 + rst_i $end
$var reg 1 ? Q_o $end
$var wire 1 2 Qbar_o $end
$upscope $end
$scope module FF4 $end
$var wire 1 @ J_i $end
$var wire 1 A K_i $end
$var wire 1 6 clk_i $end
$var wire 1 + rst_i $end
$var reg 1 B Q_o $end
$var wire 1 3 Qbar_o $end
$upscope $end
$upscope $end
$scope task check $end
$upscope $end
$upscope $end
$enddefinitions $end

#0
$dumpvars
1!
0"
1#
bx $
b0 %
b0 &
b0 '
b0 (
1)
0*
1+
x,
x-
x.
x/
x0
x1
x2
x3
x4
x5
x6
17
18
x9
1:
1;
x<
1=
1>
x?
1@
1A
xB
$end

#5000
1"
b0 $
1*
0,
0-
0.
0/
10
11
12
13
14
15
16
09
0<
0?
0B

#10000
0"
0#
0*
0+

#15000
1"
b1 $
1*
1,
00
04
19

#20000
0"
0*

#22000
b1 %
b1 &
b1 (

#25000
1"
b10 $
1*
0,
1-
10
01
14
05
09
1<

#30000
0"
0*

#32000
b10 %
b10 &
b10 (

#35000
1"
b11 $
1*
1,
00
04
19

#40000
0"
0*

#42000
b11 %
b11 &
b11 (

#45000
1"
b100 $
1*
0,
0-
1.
10
11
02
14
15
06
09
0<
1?

#50000
0"
0*

#52000
b100 %
b100 &
b100 (

#55000
1"
b101 $
1*
1,
00
04
19

#60000
0"
0*

#62000
b101 %
b101 &
b101 (

#65000
1"
b110 $
1*
0,
1-
10
01
14
05
09
1<

#70000
0"
0*

#72000
b110 %
b110 &
b110 (

#75000
1"
b111 $
1*
1,
00
04
19

#80000
0"
0*

#82000
b111 %
b111 &
b111 (

#85000
1"
b1000 $
1*
0,
0-
0.
1/
10
11
12
03
14
15
16
09
0<
0?
1B

#90000
0"
0*

#92000
b1000 %
b1000 &
b1000 (

#95000
1"
b1001 $
1*
1,
00
04
19

#100000
0"
0*

#102000
b1001 %
b1001 &
b1001 (

#105000
1"
b1010 $
1*
0,
1-
10
01
14
05
09
1<

#110000
0"
0*

#112000
b1010 %
b1010 &
b1010 (

#115000
1"
b1011 $
1*
1,
00
04
19

#120000
0"
0*

#122000
b1011 %
b1011 &
b1011 (

#125000
1"
b1100 $
1*
0,
0-
1.
10
11
02
14
15
06
09
0<
1?

#130000
0"
0*

#132000
b1100 %
b1100 &
b1100 (

#135000
1"
b1101 $
1*
1,
00
04
19

#140000
0"
0*

#142000
b1101 %
b1101 &
b1101 (

#145000
1"
b1110 $
1*
0,
1-
10
01
14
05
09
1<

#150000
0"
0*

#152000
b1110 %
b1110 &
b1110 (

#155000
1"
b1111 $
1*
1,
00
04
19

#160000
0"
0*

#162000
b1111 %
b1111 &
b1111 (

#165000
1"
b0 $
1*
0,
0-
0.
0/
10
11
12
13
14
15
16
09
0<
0?
0B

#170000
0"
0*

#172000
b10000 %
b10000 &
b0 (

#175000
1"
b1 $
1*
1,
00
04
19

#180000
0"
0*

#182000
b10001 %
b10001 &
b1 (

#185000
0!
1"
b1110 $
0)
1*
0,
1-
1.
1/
10
01
02
03
04
15
16
09
1<
1?
1B

#190000
0"
0*

#192000
b10010 %
b1 '
b0 (

#195000
1"
b1101 $
1*
1,
0-
00
11
14
05
19
0<

#200000
0"
0*

#202000
b10011 %
b10 '
b1111 (

#205000
1"
b1100 $
1*
0,
10
04
09

#210000
0"
0*

#212000
b10100 %
b11 '
b1110 (

#215000
1"
b1011 $
1*
1,
1-
0.
00
01
12
14
15
06
19
1<
0?

#220000
0"
0*

#222000
b10101 %
b100 '
b1101 (

#225000
1"
b1010 $
1*
0,
10
04
09

#230000
0"
0*

#232000
b10110 %
b101 '
b1100 (

#235000
1"
b1001 $
1*
1,
0-
00
11
14
05
19
0<

#240000
0"
0*

#242000
b10111 %
b110 '
b1011 (

#245000
1"
b1000 $
1*
0,
10
04
09

#250000
0"
0*

#252000
b11000 %
b111 '
b1010 (

#255000
1"
b111 $
1*
1,
1-
1.
0/
00
01
02
13
14
15
16
19
1<
1?
0B

#260000
0"
0*

#262000
b11001 %
b1000 '
b1001 (

#265000
1"
b110 $
1*
0,
10
04
09

#270000
0"
0*

#272000
b11010 %
b1001 '
b1000 (

#275000
1"
b101 $
1*
1,
0-
00
11
14
05
19
0<

#280000
0"
0*

#282000
b11011 %
b1010 '
b111 (

#285000
1"
b100 $
1*
0,
10
04
09

#290000
0"
0*

#292000
b11100 %
b1011 '
b110 (

#295000
1"
b11 $
1*
1,
1-
0.
00
01
12
14
15
06
19
1<
0?

#300000
0"
0*

#302000
b11101 %
b1100 '
b101 (

#305000
1"
b10 $
1*
0,
10
04
09

#310000
0"
0*

#312000
b11110 %
b1101 '
b100 (

#315000
1"
b1 $
1*
1,
0-
00
11
14
05
19
0<

#320000
0"
0*

#322000
b11111 %
b1110 '
b11 (

#325000
1"
b0 $
1*
0,
10
04
09

#330000
0"
0*

#332000
b100000 %
b1111 '
b10 (

#335000
1"
b1111 $
1*
1,
1-
1.
1/
00
01
02
03
14
15
16
19
1<
1?
1B

#340000
0"
0*

#342000
b100001 %
b10000 '
b1 (

#345000
1"
b1110 $
1*
0,
10
04
09

#350000
0"
0*

#352000
b100010 %
b10001 '
b0 (

#355000
1"
b1101 $
1*
1,
0-
00
11
14
05
19
0<

#360000
0"
0*

#362000
b100011 %
b10010 '
b1111 (

#365000
1!
1"
b10 $
1)
1*
0,
1-
0.
0/
10
01
12
13
14
05
16
09
1<
0?
0B

#370000
0"
0*

#372000
b100100 %
b10011 '
b0 (

#375000
1"
b11 $
1*
1,
00
04
19

#380000
0"
0*

#382000
b100101 %
b10100 '
b1 (

#385000
1"
b100 $
1*
0,
0-
1.
10
11
02
14
15
06
09
0<
1?

#390000
0"
0*

#392000
b100110 %
b10101 '
b10 (

#395000
1"
b101 $
1*
1,
00
04
19

#400000
0"
0*

#402000
b100111 %
b10110 '
b11 (

#405000
1"
b110 $
1*
0,
1-
10
01
14
05
09
1<

#410000
0"
0*

#412000
b101000 %
b10111 '
b100 (

#415000
1"
b111 $
1*
1,
00
04
19

#420000
0"
0*

#422000
b101001 %
b11000 '
b101 (

#425000
1"
b1000 $
1*
0,
0-
0.
1/
10
11
12
03
14
15
16
09
0<
0?
1B

#430000
0"
0*

#432000
b101010 %
b11001 '
b110 (

#435000
1"
b1001 $
1*
1,
00
04
19

#440000
0"
0*

#442000
b101011 %
b11010 '
b111 (

#445000
1"
b1010 $
1*
0,
1-
10
01
14
05
09
1<

#450000
0"
0*

#452000
b101100 %
b11011 '
b1000 (

#455000
1"
b1011 $
1*
1,
00
04
19

#460000
0"
0*

#462000
b101101 %
b11100 '
b1001 (

#465000
0!
1"
b100 $
0)
1*
0,
0-
1.
0/
10
11
02
13
04
05
16
09
0<
1?
0B

#470000
0"
0*

#472000
b101110 %
b11101 '
b1000 (

#475000
1"
b11 $
1*
1,
1-
0.
00
01
12
14
15
06
19
1<
0?

#480000
0"
0*

#482000
b101111 %
b11110 '
b111 (

#485000
1"
b10 $
1*
0,
10
04
09

#490000
0"
0*

#492000
b110000 %
b11111 '
b110 (

#495000
1"
b1 $
1*
1,
0-
00
11
14
05
19
0<

#500000
0"
0*

#502000
b110001 %
b100000 '
b101 (

#505000
1"
b0 $
1*
0,
10
04
09

#510000
0"
0*

#512000
b110010 %
b100001 '
b100 (

#515000
1!
1"
b1111 $
1)
1*
1,
1-
1.
1/
00
01
02
03
04
05
06
19
1<
1?
1B

#520000
0"
0*

#522000
b110011 %
b100010 '
b101 (

#525000
1"
b0 $
1*
0,
0-
0.
0/
10
11
12
13
14
15
16
09
0<
0?
0B

#530000
0"
0*

#532000
b110100 %
b100011 '
b110 (

#535000
1"
b1 $
1*
1,
00
04
19

#540000
0"
0*

#542000
b110101 %
b100100 '
b111 (

#545000
0!
1"
b1110 $
0)
1*
0,
1-
1.
1/
10
01
02
03
04
15
16
09
1<
1?
1B

#550000
0"
0*

#552000
b110110 %
b100101 '
b110 (

